arxiv_tool_analyzer/__init__.py
arxiv_tool_analyzer/arxiv_search.py
arxiv_tool_analyzer/merge_files.py
arxiv_tool_analyzer/search_terms.py
arxiv_tool_analyzer-0.1.3.dist-info/METADATA
arxiv_tool_analyzer-0.1.3.dist-info/WHEEL
arxiv_tool_analyzer-0.1.3.dist-info/top_level.txt
arxiv_tool_analyzer-0.1.3.dist-info/RECORD
