Metadata-Version: 2.2
Name: arxiv_tool_analyzer
Version: 0.1.3
Summary: A tool to search and analyze arXiv papers
Home-page: https://github.com/nbahador/arxiv_tool_analyzer
Author: Nooshin Bahador
Author-email: nooshin.bah@gmail.com
Classifier: Programming Language :: Python :: 3
Classifier: License :: OSI Approved :: MIT License
Classifier: Operating System :: OS Independent
Requires-Python: >=3.6
Requires-Dist: arxiv
Requires-Dist: pandas
Requires-Dist: openpyxl
Dynamic: author
Dynamic: author-email
Dynamic: classifier
Dynamic: home-page
Dynamic: requires-dist
Dynamic: requires-python
Dynamic: summary
